CHANGES.txt
MANIFEST.in
README.txt
__init__.py
app.ini
bootstrap.py
setup.cfg
setup.py
ztq_console/__init__.py
ztq_console/tests.py
ztq_console/views.py
ztq_console.egg-info/PKG-INFO
ztq_console.egg-info/SOURCES.txt
ztq_console.egg-info/dependency_links.txt
ztq_console.egg-info/entry_points.txt
ztq_console.egg-info/not-zip-safe
ztq_console.egg-info/requires.txt
ztq_console.egg-info/top_level.txt
ztq_console/static/jquery-1.6.2.min.js
ztq_console/static/jquery.js
ztq_console/static/script.js
ztq_console/static/style.css
ztq_console/static/style_login.css
ztq_console/static/images/alert.gif
ztq_console/static/images/close.gif
ztq_console/static/images/down.gif
ztq_console/static/images/header-bg.jpg
ztq_console/static/images/logo.gif
ztq_console/static/images/ok.gif
ztq_console/static/images/open.gif
ztq_console/static/images/up.gif
ztq_console/templates/errorlog.html
ztq_console/templates/jobs.html
ztq_console/templates/login.pt
ztq_console/templates/main.html
ztq_console/templates/mainpage.html
ztq_console/templates/menu.html
ztq_console/templates/password.pt
ztq_console/templates/queues.html
ztq_console/templates/syslog.html
ztq_console/templates/top.html
ztq_console/templates/worker.html
ztq_console/templates/workerlog.html
ztq_console/utils/__init__.py
ztq_console/utils/dispatch.py
ztq_console/utils/get_fts_data.py
ztq_console/utils/models.py
ztq_console/utils/password.py
ztq_console/utils/security.py