Metadata-Version: 1.1
Name: ztq-console
Version: 1.2.5
Summary: Zopen Task Queue Console
Home-page: http://everydo.com/
Author: edo
Author-email: service@everydo.com
License: MIT
Keywords: Everydo queue monitor console async
Platform: UNKNOWN
Classifier: Development Status :: 4 - Beta
Classifier: Environment :: Web Environment
Classifier: Intended Audience :: Developers
Classifier: Programming Language :: Python
Classifier: Operating System :: OS Independent
Classifier: Topic :: Internet :: WWW/HTTP
Classifier: Framework :: Pyramid
